pyblazeb2/__init__.py
pyblazeb2/pyblazeb2.py
pyblazeb2-0.0.23.dist-info/METADATA
pyblazeb2-0.0.23.dist-info/RECORD
pyblazeb2-0.0.23.dist-info/WHEEL
pyblazeb2-0.0.23.dist-info/top_level.txt
