Metadata-Version: 2.1
Name: pyblazeb2
Version: 0.0.23
Summary: A compact library for interacting with Backblaze b2 buckets
Home-page: https://github.com/mwlong23/pyblazeb2
Author: Mitchell Long
Author-email: meechllada@gmail.com
License: UNKNOWN
Project-URL: Source, https://github.com/mwlong23/pyblazeb2
Project-URL: Tracker, https://github.com/mwlong23/pyblazeb2/issues
Platform: UNKNOWN
Classifier: Development Status :: 3 - Alpha
Classifier: Intended Audience :: Developers
Classifier: Programming Language :: Python :: 3
Classifier: License :: OSI Approved :: MIT License
